<?xml version="1.0" encoding="utf-8" ?>
<dwsync>
<file name="acceder.png" server="185.28.21.67//public_html/" local="129890240080000000" remote="130251119400000000" Dst="2" />
<file name="admin-archivo.jpg" server="185.28.21.67//public_html/" local="129892627280000000" remote="130251119400000000" Dst="2" />
<file name="admin-calendario.jpg" server="185.28.21.67//public_html/" local="129892637200000000" remote="130251120000000000" Dst="2" />
<file name="admin.jpg" server="185.28.21.67//public_html/" local="129892637560000000" remote="130251120000000000" Dst="2" />
<file name="banner-n-1.png" server="185.28.21.67//public_html/" local="129902973460000000" remote="130251120000000000" Dst="2" />
<file name="banner-n-2.png" server="185.28.21.67//public_html/" local="129902988740000000" remote="130251120000000000" Dst="2" />
<file name="banner-n-3.png" server="185.28.21.67//public_html/" local="129903147960000000" remote="130251120000000000" Dst="2" />
<file name="banner-n-4.png" server="185.28.21.67//public_html/" local="129902994260000000" remote="130251120000000000" Dst="2" />
<file name="banner-n-5.png" server="185.28.21.67//public_html/" local="129902995800000000" remote="130251120000000000" Dst="2" />
<file name="bg_direction_nav.png" server="185.28.21.67//public_html/" local="129881467480000000" remote="130251120000000000" Dst="2" />
<file name="bienvenido.png" server="185.28.21.67//public_html/" local="129893426680000000" remote="130251120000000000" Dst="2" />
<file name="calendario.jpg" server="185.28.21.67//public_html/" local="129891997220000000" remote="130251120000000000" Dst="2" />
<file name="carpeta1.jpg" server="185.28.21.67//public_html/" local="129903038520000000" remote="130251120000000000" Dst="2" />
<file name="carpeta2.jpg" server="185.28.21.67//public_html/" local="129903038640000000" remote="130251120000000000" Dst="2" />
<file name="cerrar-sesion.png" server="185.28.21.67//public_html/" local="129891103480000000" remote="130251120000000000" Dst="2" />
<file name="dir-operaciones.jpg" server="185.28.21.67//public_html/" local="129899779160000000" remote="130251120000000000" Dst="2" />
<file name="direccion-general.jpg" server="185.28.21.67//public_html/" local="129891126000000000" remote="130251120000000000" Dst="2" />
<file name="direccion-operaciones.jpg" server="185.28.21.67//public_html/" local="129899774160000000" remote="130251120000000000" Dst="2" />
<file name="footer.png" server="185.28.21.67//public_html/" local="130251708838811399" remote="130251865200000000" Dst="2" />
<file name="foto1.jpg" server="185.28.21.67//public_html/" local="129890257320000000" remote="130251120000000000" Dst="2" />
<file name="foto2.jpg" server="185.28.21.67//public_html/" local="129891113360000000" remote="130251120000000000" Dst="2" />
<file name="foto3.jpg" server="185.28.21.67//public_html/" local="129891113100000000" remote="130251120000000000" Dst="2" />
<file name="frase-n.png" server="185.28.21.67//public_html/" local="129902973460000000" remote="130251120000000000" Dst="2" />
<file name="info-archivo.jpg" server="185.28.21.67//public_html/" local="129893455460000000" remote="130251120000000000" Dst="2" />
<file name="inicio-icon-b.png" server="185.28.21.67//public_html/" local="129890885760000000" remote="130251120000000000" Dst="2" />
<file name="inicio-icon.png" server="185.28.21.67//public_html/" local="129890257320000000" remote="130251120000000000" Dst="2" />
<file name="login.jpg" server="185.28.21.67//public_html/" local="129893466480000000" remote="130251120000000000" Dst="2" />
<file name="logo-admin.png" server="185.28.21.67//public_html/" local="129891077080000000" remote="130251120000000000" Dst="2" />
<file name="logo.png" server="185.28.21.67//public_html/" local="130251832169755526" remote="130251869400000000" Dst="2" />
<file name="menu.jpg" server="185.28.21.67//public_html/" local="129890257320000000" remote="130251120000000000" Dst="2" />
<file name="morelinks-icon-b.png" server="185.28.21.67//public_html/" local="129890940940000000" remote="130251120000000000" Dst="2" />
<file name="morelinks-icon.png" server="185.28.21.67//public_html/" local="129890257320000000" remote="130251120000000000" Dst="2" />
<file name="negro60.png" server="185.28.21.67//public_html/" local="129888426120000000" remote="130251120000000000" Dst="2" />
<file name="noticias-n.png" server="185.28.21.67//public_html/" local="129902973460000000" remote="130251120000000000" Dst="2" />
<file name="oma-logo.png" server="185.28.21.67//public_html/" local="130251833681862014" remote="130251869400000000" Dst="2" />
<file name="perfil.jpg" server="185.28.21.67//public_html/" local="129903060680000000" remote="130251120600000000" Dst="2" />
<file name="portada-body.jpg" server="185.28.21.67//public_html/" local="129893441900000000" remote="130251120600000000" Dst="2" />
<file name="square_bg copy.png" server="185.28.21.67//public_html/" local="129841751440000000" remote="130251120600000000" Dst="2" />
<file name="square_bg.png" server="185.28.21.67//public_html/" local="129890928780000000" remote="130251120600000000" Dst="2" />
<file name="transp.gif" server="185.28.21.67//public_html/" local="129798745960000000" remote="130251120600000000" Dst="2" />
<file name="triangulito-gris.jpg" server="185.28.21.67//public_html/" local="129890874280000000" remote="130251120600000000" Dst="2" />
</dwsync>